budserve/__init__.py
budserve-0.0.1.dist-info/LICENSE
budserve-0.0.1.dist-info/METADATA
budserve-0.0.1.dist-info/WHEEL
budserve-0.0.1.dist-info/top_level.txt
budserve-0.0.1.dist-info/RECORD
