Metadata-Version: 2.1
Name: budserve
Version: 0.0.1
Summary: A client package to directly integrate Bud Serve engine to your python application.
Home-page: https://github.com/BudEcosystem/bud-serve-sdk
Classifier: Programming Language :: Python :: 3
Classifier: License :: OSI Approved :: Apache Software License
Classifier: Operating System :: OS Independent
Requires-Python: >=3.10
License-File: LICENSE
Requires-Dist: guidance ==0.1.15
Requires-Dist: transformers
